{
  "type": "panel",
  "name": "Network Weathermap",
  "id": "knightss27-network-weathermap",
  "info": {
    "description": "A simple & sleek network weathermap, built completely with SVG components.",
    "author": {
      "name": "knightss@catlin.edu",
      "url": "https://seth.cx"
    },
    "keywords": ["network", "weathermap", "network weathermap"],
    "logos": {
      "small": "img/logo.svg",
      "large": "img/logo.svg"
    },
    "links": [
      {
        "name": "Website",
        "url": "https://github.com/grafana/simple-react-panel"
      },
      {
        "name": "License",
        "url": "https://github.com/grafana/simple-react-panel/blob/master/LICENSE"
      }
    ],
    "screenshots": [],
    "version": "%VERSION%",
    "updated": "%TODAY%"
  },
  "dependencies": {
    "grafanaVersion": "7.0.x",
    "plugins": []
  }
}
